pb/__init__.py
pb/example_pb2.py
pb2df/__init__.py
pb2df-1.0.0.dist-info/METADATA
pb2df-1.0.0.dist-info/WHEEL
pb2df-1.0.0.dist-info/top_level.txt
pb2df-1.0.0.dist-info/RECORD
