Metadata-Version: 2.1
Name: pb2df
Version: 1.0.0
Summary: A python module for converting proto3 type/object to spark dataframe object.
Home-page: https://github.com/zhangxianbing/pb2df
Author: Xianbing Zhang
Author-email: zhangxianbing09@163.com
License: UNKNOWN
Platform: any
Requires-Dist: protobuf (>=3.13.0)
Requires-Dist: pyspark (>=3.0.0)
